example.py
lmstudio_client/__init__.py
lmstudio_client/chat_service.py
lmstudio_client/client.py
lmstudio_client-0.1.0.dist-info/METADATA
lmstudio_client-0.1.0.dist-info/WHEEL
lmstudio_client-0.1.0.dist-info/top_level.txt
lmstudio_client-0.1.0.dist-info/RECORD
