Metadata-Version: 2.2
Name: lmstudio_client
Version: 0.1.0
Summary: A lightweight Python client for interacting with LM Studio API.
Author: Eiredynamic
Project-URL: Homepage, https://github.com/eiredynamic/lmstudio-client-python
Project-URL: Repository, https://github.com/eiredynamic/lmstudio-client-python
Project-URL: Bug Tracker, https://github.com/eiredynamic/lmstudio-client-python/issues
Classifier: Programming Language :: Python :: 3
Classifier: License :: OSI Approved :: MIT License
Classifier: Operating System :: OS Independent
Requires-Python: >=3.10
Requires-Dist: requests>=2.32.2
